parmancer/__init__.py
parmancer/parser.py
parmancer/py.typed
parmancer/text_display.py
parmancer-0.2.0.dist-info/METADATA
parmancer-0.2.0.dist-info/WHEEL
parmancer-0.2.0.dist-info/licenses/LICENSE
parmancer-0.2.0.dist-info/RECORD
