Metadata-Version: 2.4
Name: parmancer
Version: 0.2.0
Summary: Parse structured data from text using parser combinators
Project-URL: Repository, https://github.com/parmancer/parmancer
Project-URL: Documentation, https://parmancer.com
Author-email: Rob Hornby <robjhornby@gmail.com>
License-Expression: MIT
License-File: LICENSE
Keywords: parser,parser combinator,parsing
Classifier: Development Status :: 3 - Alpha
Classifier: Programming Language :: Python :: 3.8
Classifier: Programming Language :: Python :: 3.9
Classifier: Programming Language :: Python :: 3.10
Classifier: Programming Language :: Python :: 3.11
Classifier: Programming Language :: Python :: 3.12
Classifier: Topic :: File Formats
Classifier: Topic :: Software Development :: Compilers
Classifier: Topic :: Software Development :: Interpreters
Classifier: Topic :: Text Processing
Classifier: Typing :: Typed
Requires-Python: >=3.8
Requires-Dist: typing-extensions>=4.5.0
